[
  {
    "source": "MySQL_rdc_dv_tape_out_lookup.csv",
    "data": {
      "IP": "RLE1339",
      "TIMESTAMP": "2024-03-05 00:20:42",
      "TPO_DATE": "2024-10-15",
      "REG_FLAG": "N"
    }
  },
  {
    "source": "MySQL_rdc_dv_tape_out_lookup.csv",
    "data": {
      "IP": "RL6693",
      "TIMESTAMP": "2024-03-05 00:20:42",
      "TPO_DATE": "2024-10-15",
      "REG_FLAG": "N"
    }
  },
  {
    "source": "MySQL_rdc_dv_report_hist.csv",
    "data": {
      "UPD_DATE": "2020/10/12 00:00",
      "DATE": "2020/10/12",
      "PROJECT": "afe",
      "IP": "RLE1339",
      "DV_TYPE": "FULL",
      "PASSED": "77/89",
      "COVERAGE": "76.02/17.44",
      "FOLDER_PATH": "/project/Digital_HS/xxx",
      "UNCOVERED": NaN,
      "RTL_UPDATE_DATE": NaN,
      "RELEASE_TO_BU_DATE": NaN,
      "TAPEOUT_DATE": NaN,
      "VALID": 1,
      "PROJECT_REPOS": "ssh://rdgerrit.xxx",
      "REGRESSION_MAKEFILE": NaN,
      "SVN_REV": 18920,
      "SVN_PATH": "http://dtdinfo/svn/RD/xxx",
      "RTL_SRC_PATH": NaN,
      "RTL_SRC_FLIST": NaN,
      "RTL_SRC_TB": NaN,
      "DEST_SVN": NaN,
      "COMMENT": NaN
    }
  },
  {
    "source": "MySQL_rdc_dv_report_hist.csv",
    "data": {
      "UPD_DATE": "2020/10/12 00:00",
      "DATE": "2020/10/12",
      "PROJECT": "pcie_ts",
      "IP": "RLE993_2x1",
      "DV_TYPE": "FULL",
      "PASSED": "77/89",
      "COVERAGE": "76.02/17.44",
      "FOLDER_PATH": "/project/Digital_HS/xxx",
      "UNCOVERED": NaN,
      "RTL_UPDATE_DATE": NaN,
      "RELEASE_TO_BU_DATE": NaN,
      "TAPEOUT_DATE": NaN,
      "VALID": 1,
      "PROJECT_REPOS": "ssh://rdgerrit.xxx",
      "REGRESSION_MAKEFILE": NaN,
      "SVN_REV": 18920,
      "SVN_PATH": "http://dtdinfo/svn/RD/xxx",
      "RTL_SRC_PATH": NaN,
      "RTL_SRC_FLIST": NaN,
      "RTL_SRC_TB": NaN,
      "DEST_SVN": NaN,
      "COMMENT": NaN
    }
  }
]